{
  "categories": [
    {
      "name": "Cat_1 up",
      "createdTime": "2023-02-18T13:36:35.247Z",
      "id": 3
    },
    {
      "name": "Cat_2 up",
      "createdTime": "2023-02-20T12:28:19.356Z",
      "id": 4
    }
  ],
  "products": [
    {
      "name": "T-Shirt",
      "price": "100",
      "quantity": "100",
      "description": "T-shirt Test",
      "image": "https://www.machinescreenprinters.com.au/wp-content/uploads/2021/10/alstyle_1301_gold.jpg",
      "createdTime": "2023-02-18T13:36:59.314Z",
      "categoryId": "4",
      "id": 1
    },
    {
      "name": "shirt",
      "price": "23",
      "quantity": "123",
      "description": "T-shirt Test",
      "image": "https://www.machinescreenprinters.com.au/wp-content/uploads/2021/10/alstyle_1301_gold.jpg",
      "createdTime": "2023-02-18T13:31:17.652Z",
      "categoryId": "3",
      "id": 2
    },
    {
      "name": "ttt",
      "price": "4",
      "quantity": "129",
      "description": "P222",
      "image": "https://www.machinescreenprinters.com.au/wp-content/uploads/2021/10/alstyle_1301_gold.jpg",
      "categoryId": "4",
      "createdTime": "2023-02-20T12:48:23.916Z",
      "id": 3
    }
  ]
}